cdk_mwaa/__init__.py
cdk_mwaa/py.typed
cdk_mwaa/_jsii/__init__.py
cdk_mwaa/_jsii/cdk-mwaa@0.0.29.jsii.tgz
cdk_mwaa-0.0.29.dist-info/LICENSE
cdk_mwaa-0.0.29.dist-info/METADATA
cdk_mwaa-0.0.29.dist-info/WHEEL
cdk_mwaa-0.0.29.dist-info/top_level.txt
cdk_mwaa-0.0.29.dist-info/RECORD
