Metadata-Version: 2.1
Name: cdk-mwaa
Version: 0.0.29
Summary: AWS CDK construct library for Amazon Managed Workflows for Apache Airflow (MWAA)
Home-page: https://github.com/hupe1980/cdk-mwaa.git
Author: hupe1980<frankhuebner1980@gmail.com>
License: MIT
Project-URL: Source, https://github.com/hupe1980/cdk-mwaa.git
Classifier: Intended Audience :: Developers
Classifier: Operating System :: OS Independent
Classifier: Programming Language :: JavaScript
Classifier: Programming Language :: Python :: 3 :: Only
Classifier: Programming Language :: Python :: 3.9
Classifier: Programming Language :: Python :: 3.10
Classifier: Programming Language :: Python :: 3.11
Classifier: Typing :: Typed
Classifier: Development Status :: 5 - Production/Stable
Classifier: License :: OSI Approved
Requires-Python: ~=3.9
License-File: LICENSE
Requires-Dist: aws-cdk-lib<3.0.0,>=2.185.0
Requires-Dist: constructs<11.0.0,>=10.0.5
Requires-Dist: jsii<2.0.0,>=1.111.0
Requires-Dist: publication>=0.0.3
Requires-Dist: typeguard<4.3.0,>=2.13.3
